.coveragerc
.hgignore
CHANGES.txt
COPYRIGHT.txt
HACKING.txt
LICENSE.txt
README.txt
bootstrap.py
buildout.cfg
setup.py
src/pyblz/BLZ_20120903.txt
src/pyblz/__init__.py
src/pyblz/parse.py
src/pyblz.egg-info/PKG-INFO
src/pyblz.egg-info/SOURCES.txt
src/pyblz.egg-info/dependency_links.txt
src/pyblz.egg-info/not-zip-safe
src/pyblz.egg-info/requires.txt
src/pyblz.egg-info/top_level.txt
src/pyblz/tests/__init__.py
src/pyblz/tests/test_parse.py