Metadata-Version: 1.1
Name: pyblz
Version: 20120903
Summary: Wrapper around BLZ data from Deutsche Bundesbank
Home-page: https://projects.gocept.com/projects/pyblz/
Author: Wolfgang Schnerring <ws@gocept.com>
Author-email: ws@gocept.com
License: ZPL 2.1
Platform: UNKNOWN
Classifier: License :: OSI Approved :: Zope Public License
Classifier: Programming Language :: Python
Classifier: Programming Language :: Python :: 2
Classifier: Programming Language :: Python :: 2.6
Classifier: Programming Language :: Python :: 2.7
Classifier: Programming Language :: Python :: 2 :: Only
